bonsai_gym/__init__.py
bonsai_gym/gym_simulator.py
bonsai_gym/luminance_gym_simulator.py
bonsai_gym/version.py
bonsai_gym-2.0.13.dist-info/LICENSE.txt
bonsai_gym-2.0.13.dist-info/METADATA
bonsai_gym-2.0.13.dist-info/WHEEL
bonsai_gym-2.0.13.dist-info/top_level.txt
bonsai_gym-2.0.13.dist-info/RECORD
