Metadata-Version: 2.1
Name: bonsai-gym
Version: 2.0.13
Summary: A python library for integrating Bonsai BRAIN     with Open AI Gym environments.
Home-page: https://bons.ai
Author: Bonsai, Inc.
Author-email: opensource@bons.ai
License: BSD
Keywords: bonsai
Platform: UNKNOWN
Classifier: Development Status :: 4 - Beta
Classifier: Intended Audience :: Developers
Classifier: Topic :: Scientific/Engineering :: Artificial Intelligence
Classifier: License :: OSI Approved :: BSD License
Classifier: Programming Language :: Python :: 2.7
Classifier: Programming Language :: Python :: 3.5
Classifier: Programming Language :: Python :: 3.6
Classifier: Natural Language :: English
Requires-Python: >=2.7, !=3.0.*, !=3.1.*, !=3.2.*, !=3.3.*, !=3.4.*
Requires-Dist: bonsai-ai (>=2.0.19)
Requires-Dist: gym (==0.9.7)
